{
  "response": [
    {
      "dateStr": "09.05. 12:00",
      "home": "Barakaldo",
      "away": "AD Mérida",
      "score_home": "-",
      "score_away": "-",
      "status": "NS"
    },
    {
      "dateStr": "17.05. 15:00",
      "home": "AD Mérida",
      "away": "Unionistas",
      "score_home": "-",
      "score_away": "-",
      "status": "NS"
    },
    {
      "dateStr": "23.05. 16:30",
      "home": "Osasuna B",
      "away": "AD Mérida",
      "score_home": "-",
      "score_away": "-",
      "status": "NS"
    }
  ]
}